etrainee_m4_utils/__init__.py
etrainee_m4_utils/hs_classification.py
etrainee_m4_utils/image_preprocessing.py
etrainee_m4_utils/inference_utils.py
etrainee_m4_utils/visualisation_utils.py
etrainee_m4_utils-0.2.2.dist-info/LICENSE
etrainee_m4_utils-0.2.2.dist-info/METADATA
etrainee_m4_utils-0.2.2.dist-info/WHEEL
etrainee_m4_utils-0.2.2.dist-info/top_level.txt
etrainee_m4_utils-0.2.2.dist-info/RECORD
